[
  { "name": "Adobe Experience Platform", "file": "adobe_experience_platform" },
  { "name": "React", "file": "react" },
  { "name": "Laravel", "file": "laravel" },
  { "name": "Javascript", "file": "javascript" },
  { "name": ".NET", "file": "dotnet" },
  { "name": "WordPress", "file": "word_press" },
  { "name": "MySQL", "file": "my_sql" },
  { "name": "PHP", "file": "php" },
  { "name": "Python", "file": "python" },
  { "name": "Kotlin", "file": "kotlin" },
  { "name": "Java", "file": "java" },
  { "name": "C#", "file": "c_sharp" },
  { "name": "HTML", "file": "html" },
  { "name": "CSS", "file": "css" },
  { "name": "Android Studio", "file": "android_studio" },
  { "name": "Unity", "file": "unity" },
  { "name": "GIT", "file": "git" },
  { "name": "GitHub", "file": "git_hub" },
  { "name": "Postman", "file": "postman" }
]
